powerwiki/__init__.py
powerwiki/admin.py
powerwiki/app_settings.py
powerwiki/archive.py
powerwiki/constants.py
powerwiki/decorators.py
powerwiki/forms.py
powerwiki/html.py
powerwiki/models.py
powerwiki/urls.py
powerwiki/utils.py
powerwiki/views.py
powerwiki/markup/__init__.py
powerwiki/markup/base.py
powerwiki/markup/loader.py
powerwiki/markup/md.py
powerwiki/markup/plain.py
powerwiki/markup/rest.py
powerwiki/migrations/0001_initial.py
powerwiki/migrations/0002_page_depth.py
powerwiki/migrations/0003_set_depth.py
powerwiki/migrations/0004_wiki_archived_wiki_logo.py
powerwiki/migrations/__init__.py
powerwiki/static/powerwiki/index.css
powerwiki/static/powerwiki/index.js
powerwiki/static/powerwiki/index.js.map
powerwiki/static/powerwiki/logo_default.svg
powerwiki/templates/powerwiki/asset_details.html
powerwiki/templates/powerwiki/asset_edit.html
powerwiki/templates/powerwiki/base.html
powerwiki/templates/powerwiki/edit.html
powerwiki/templates/powerwiki/import.html
powerwiki/templates/powerwiki/index.html
powerwiki/templates/powerwiki/search.html
powerwiki/templates/powerwiki/show.html
powerwiki/templates/powerwiki/includes/breadcrumbs.html
powerwiki/templates/powerwiki/includes/search.html
powerwiki/templatetags/__init__.py
powerwiki/templatetags/powerwiki.py
django_powerwiki-0.5.1.dist-info/LICENSE
django_powerwiki-0.5.1.dist-info/METADATA
django_powerwiki-0.5.1.dist-info/WHEEL
django_powerwiki-0.5.1.dist-info/top_level.txt
django_powerwiki-0.5.1.dist-info/RECORD
