Metadata-Version: 2.1
Name: django-powerwiki
Version: 0.5.1
Summary: A wiki system for Django
Author-email: Richard Terry <code@radiac.net>
Project-URL: Homepage, https://radiac.net/projects/django-powerwiki/
Project-URL: Documentation, https://django-powerwiki.readthedocs.io/en/latest/
Project-URL: Source, https://github.com/radiac/django-powerwiki
Project-URL: Bug Tracker, https://github.com/radiac/django-powerwiki/issues
Keywords: django,wiki
Classifier: Development Status :: 4 - Beta
Classifier: Framework :: Django
Classifier: License :: OSI Approved :: BSD License
Classifier: Programming Language :: Python :: 3
Classifier: Operating System :: OS Independent
Requires-Python: >=3.7
License-File: LICENSE
Requires-Dist: Django>=3.2
Requires-Dist: django-yaa-settings
Requires-Dist: beautifulsoup4
Requires-Dist: docutils
Requires-Dist: markdown
